era5_torch/__init__.py
era5_torch/_auxiliaries.py
era5_torch/_chunkers.py
era5_torch/_dataset_class.py
era5_torch/_patchers.py
era5_torch-0.1.1.dist-info/LICENSE.MIT
era5_torch-0.1.1.dist-info/METADATA
era5_torch-0.1.1.dist-info/WHEEL
era5_torch-0.1.1.dist-info/top_level.txt
era5_torch-0.1.1.dist-info/RECORD
