Metadata-Version: 2.1
Name: era5_torch
Version: 0.1.1
Summary: PyTorch-compatible wrapper for Era5
Author-email: Alexander Conzelmann <a.conzelmann@student.uni-tuebingen.de>
Requires-Python: >=3.9
License-File: LICENSE.MIT
Requires-Dist: torch
Requires-Dist: torchvision
Requires-Dist: xarray
Requires-Dist: numpy
